[
    {
        "OSDVersion":  "2025.9.9.1",
        "Id":  "f7b69dc0-a79b-470d-8ef4-489837fecd87",
        "Title":  "2022-12 Security Update for Windows 10 Version 22H2 for x64-based Systems (KB5012170)",
        "LegacyName":  "KB5012170-Windows1022H2-RTM-StandaloneSecurity-X64-TSL-World",
        "KBNumber":  "5012170",
        "CreationDate":  "2022-12-13T18:03:06Z",
        "UpdateArch":  "x64",
        "UpdateGroup":  "Optional",
        "FileKBNumber":  "5012170",
        "FileUri":  "http://download.windowsupdate.com/d/msdownload/update/software/secu/2022/08/windows10.0-kb5012170-x64_b120c3bdd40329520f54950d20d053d1e7660faa.cab",
        "AdditionalHash":  "83 187 11 64 41 232 156 150 164 222 85 65 186 112 76 34 52 253 142 229 85 67 211 252 20 42 55 116 224 227 245 221"
    },
    {
        "OSDVersion":  "2025.9.9.1",
        "Id":  "369cd8c2-1e7e-49ba-a604-b0095b745159",
        "Title":  "Microsoft .NET Framework 4.8.1 for Windows 10 Version 22H2 for x64 (KB5011048)",
        "LegacyName":  "KB5011048-DotNetStandalone-22H2-Client-x64-Retail",
        "KBNumber":  "5011048",
        "CreationDate":  "2023-06-27T17:00:00Z",
        "UpdateArch":  "x64",
        "UpdateGroup":  "DotNet",
        "FileKBNumber":  "5011048",
        "FileUri":  "http://download.windowsupdate.com/d/msdownload/update/software/ftpk/2023/05/windows10.0-kb5011048-x64_60754528508631de484f430ca1b3bba317454ae1.cab",
        "AdditionalHash":  "116 59 241 74 54 5 174 38 35 79 67 235 33 67 161 174 38 210 18 186 35 153 156 24 255 105 253 55 210 217 122 3"
    },
    {
        "OSDVersion":  "2025.9.9.1",
        "Id":  "f4fce270-a397-467f-b121-aa24991da4e5",
        "Title":  "2023-10 Servicing Stack Update for Windows 10 Version 22H2 for x64-based Systems (KB5031539)",
        "LegacyName":  "KB5031539-Windows1022H2-RTM-ServicingStackUpdate-X64-TSL-World",
        "KBNumber":  "5031539",
        "CreationDate":  "2023-10-10T17:00:06Z",
        "UpdateArch":  "x64",
        "UpdateGroup":  "SSU",
        "FileKBNumber":  "5031539",
        "FileUri":  "http://download.windowsupdate.com/c/msdownload/update/software/secu/2023/10/ssu-19041.3562-x64_bf1e4bd96a843cc56a3127ca721a5415ff3100e6.cab",
        "AdditionalHash":  "105 40 9 41 186 0 97 241 63 238 9 223 171 3 169 113 221 18 126 186 53 128 236 149 126 233 59 225 107 89 240 98"
    },
    {
        "OSDVersion":  "2025.9.9.1",
        "Id":  "be5ebf62-6260-45ba-9229-f3fe2368ceed",
        "Title":  "2025-01 Cumulative Update for .NET Framework 3.5, 4.8 and 4.8.1 for Windows 10 Version 22H2 for x64 (KB5050188)",
        "LegacyName":  "KB5050188-DotNetCumulative-22H2-Client-x64-Retail",
        "KBNumber":  "5050188",
        "CreationDate":  "2025-01-14T18:00:00Z",
        "UpdateArch":  "x64",
        "UpdateGroup":  "DotNetCU",
        "FileKBNumber":  "5049621",
        "FileUri":  "http://download.windowsupdate.com/d/msdownload/update/software/secu/2024/12/windows10.0-kb5049621-x64-ndp481_f017f865df2782a6ece2d5afc300c04cb553019d.cab",
        "AdditionalHash":  "245 64 195 46 130 87 138 225 158 7 126 139 26 86 118 1 18 29 89 36 108 51 174 201 1 163 190 163 133 147 213 107"
    },
    {
        "OSDVersion":  "2025.9.9.1",
        "Id":  "be5ebf62-6260-45ba-9229-f3fe2368ceed",
        "Title":  "2025-01 Cumulative Update for .NET Framework 3.5, 4.8 and 4.8.1 for Windows 10 Version 22H2 for x64 (KB5050188)",
        "LegacyName":  "KB5050188-DotNetCumulative-22H2-Client-x64-Retail",
        "KBNumber":  "5050188",
        "CreationDate":  "2025-01-14T18:00:00Z",
        "UpdateArch":  "x64",
        "UpdateGroup":  "DotNetCU",
        "FileKBNumber":  "5049613",
        "FileUri":  "http://download.windowsupdate.com/d/msdownload/update/software/secu/2024/12/windows10.0-kb5049613-x64-ndp48_653c294e1288922430d9be4ce2a80b9ccbc44247.cab",
        "AdditionalHash":  "106 54 140 65 117 123 21 249 64 114 189 255 166 209 251 190 146 77 242 99 194 159 32 156 79 237 247 106 58 53 118 197"
    },
    {
        "OSDVersion":  "2025.9.9.1",
        "Id":  "2680c385-659a-4326-bcee-1f786b07cefc",
        "Title":  "2025-09 Cumulative Update for Windows 10 Version 22H2 for x64-based Systems (KB5065429)",
        "LegacyName":  "KB5065429-UnifiedCumulative-22H2-Client-x64-Retail",
        "KBNumber":  "5065429",
        "CreationDate":  "2025-09-09T17:00:00Z",
        "UpdateArch":  "x64",
        "UpdateGroup":  "Optional",
        "FileKBNumber":  "5065429",
        "FileUri":  "http://download.windowsupdate.com/c/msdownload/update/software/secu/2025/09/windows10.0-kb5065429-x64_10c9cbda4a65519b3046356b15c52e0615f259d4.cab",
        "AdditionalHash":  "176 187 179 209 111 139 172 215 61 2 147 198 247 245 31 58 221 131 11 175 16 39 82 106 100 116 167 67 50 168 91 67"
    },
    {
        "OSDVersion":  "2025.9.9.1",
        "Id":  "dfa48f65-1601-4c64-8b01-07f9ed4e1b46",
        "Title":  "2025-09 Cumulative Update for .NET Framework 3.5, 4.8 and 4.8.1 for Windows 10 Version 22H2 for x64 (KB5065957)",
        "LegacyName":  "KB5065957-DotNetCumulative-22H2-Client-x64-Retail",
        "KBNumber":  "5065957",
        "CreationDate":  "2025-09-09T17:00:00Z",
        "UpdateArch":  "x64",
        "UpdateGroup":  "DotNetCU",
        "FileKBNumber":  "5064399",
        "FileUri":  "http://download.windowsupdate.com/c/msdownload/update/software/updt/2025/07/windows10.0-kb5064399-x64-ndp48_92219fe86733fcb27c3e7ea4d08e1f404c33b30a.cab",
        "AdditionalHash":  "192 209 134 253 175 157 112 107 108 173 74 52 237 70 109 83 161 192 69 205 52 69 169 173 139 87 93 144 15 165 205 4"
    },
    {
        "OSDVersion":  "2025.9.9.1",
        "Id":  "dfa48f65-1601-4c64-8b01-07f9ed4e1b46",
        "Title":  "2025-09 Cumulative Update for .NET Framework 3.5, 4.8 and 4.8.1 for Windows 10 Version 22H2 for x64 (KB5065957)",
        "LegacyName":  "KB5065957-DotNetCumulative-22H2-Client-x64-Retail",
        "KBNumber":  "5065957",
        "CreationDate":  "2025-09-09T17:00:00Z",
        "UpdateArch":  "x64",
        "UpdateGroup":  "DotNetCU",
        "FileKBNumber":  "5064400",
        "FileUri":  "http://download.windowsupdate.com/d/msdownload/update/software/updt/2025/07/windows10.0-kb5064400-x64-ndp481_842bd34df8cda1085d5e23132829b418ef81829d.cab",
        "AdditionalHash":  "213 110 103 224 99 223 195 98 28 213 30 45 194 171 79 146 199 117 95 0 10 152 31 220 237 8 92 53 213 87 54 44"
    }
]